{
	"info": {
		"_postman_id": "dafce1ae-9149-43cf-a3c7-a108a08491d0",
		"name": "Teste ServerRest",
		"schema": "https://schema.getpostman.com/json/collection/v2.0.0/collection.json"
	},
	"item": [
		{
			"name": "Produtos",
			"item": [
				{
					"name": "Listar produtos",
					"event": [
						{
							"listen": "test",
							"script": {
								"exec": [
									"pm.test(\"Status code is 200\", function () {\r",
									"    pm.response.to.have.status(200);\r",
									"});\r",
									"\r",
									""
								],
								"type": "text/javascript"
							}
						}
					],
					"request": {
						"method": "GET",
						"header": [],
						"url": "http://localhost:3000/produtos"
					},
					"response": []
				},
				{
					"name": "Criar produto",
					"event": [
						{
							"listen": "test",
							"script": {
								"exec": [
									"pm.test(\"Validadar mensagem de sucesso\", function () {\r",
									"    pm.expect(pm.response.text()).to.include(\"Cadastro realizado com sucess\");\r",
									"});\r",
									"\r",
									"pm.test(\"Status code is 200\", function () {\r",
									"    pm.response.to.have.status(201);\r",
									"});"
								],
								"type": "text/javascript"
							}
						}
					],
					"request": {
						"method": "POST",
						"header": [
							{
								"warning": "This is a duplicate header and will be overridden by the Authorization header generated by Postman.",
								"key": "Authorization",
								"value": "{{token}}",
								"type": "text"
							}
						],
						"body": {
							"mode": "raw",
							"raw": "{\r\n  \"nome\": \"Capinha de relógio\",\r\n  \"preco\": 35,\r\n  \"descricao\": \"Relógio\",\r\n  \"quantidade\": 24\r\n}",
							"options": {
								"raw": {
									"language": "json"
								}
							}
						},
						"url": "http://localhost:3000/produtos"
					},
					"response": []
				},
				{
					"name": "Listar produtos por id",
					"event": [
						{
							"listen": "test",
							"script": {
								"exec": [
									"pm.test(\"Validadar produtos da lista\", function () {\r",
									"    pm.expect(pm.response.text()).to.include(\"Logitech MX Vertical\");\r",
									"});\r",
									"\r",
									"pm.test(\"Status code is 200\", function () {\r",
									"    pm.response.to.have.status(200);\r",
									"});"
								],
								"type": "text/javascript"
							}
						}
					],
					"request": {
						"method": "GET",
						"header": [],
						"url": "http://localhost:3000/produtos/kyFEoOdnoOhM7ii2"
					},
					"response": []
				},
				{
					"name": "Editar produtos",
					"request": {
						"method": "PUT",
						"header": [
							{
								"key": "Authorization",
								"value": "{{token}}",
								"type": "text"
							}
						],
						"body": {
							"mode": "raw",
							"raw": "{\r\n  \"nome\": \"Logitech MX Vertical v3\",\r\n  \"preco\": \"0855\",\r\n  \"descricao\": \"Mouse\",\r\n  \"quantidade\": 822\r\n}",
							"options": {
								"raw": {
									"language": "json"
								}
							}
						},
						"url": "http://localhost:3000/produtos/BeeJh5lz3k6kSIzA"
					},
					"response": []
				},
				{
					"name": "Deletar produto",
					"event": [
						{
							"listen": "test",
							"script": {
								"exec": [
									"pm.test(\"Status code is 200\", function () {\r",
									"    pm.response.to.have.status(200);\r",
									"});\r",
									"\r",
									"pm.test(\"Validar mensagem\", function () {\r",
									"    pm.expect(pm.response.text()).to.include(\"Nenhum registro excluído\");\r",
									"});"
								],
								"type": "text/javascript"
							}
						}
					],
					"request": {
						"auth": {
							"type": "bearer",
							"bearer": {
								"token": "eyJhbGciOiJIUzI1NiIsInR5cCI6IkpXVCJ9.eyJlbWFpbCI6InRhbGlzc2FzaWx2YUBxYS5jb20uYnIiLCJwYXNzd29yZCI6InRlc3RlIiwiaWF0IjoxNjQ5MTk1Mjc4LCJleHAiOjE2NDkxOTU4Nzh9.PMQIp3qYhZJC_M-uLV2FGWZqdN83w7RNGQj5OG-dkxk"
							}
						},
						"method": "DELETE",
						"header": [],
						"body": {
							"mode": "raw",
							"raw": "",
							"options": {
								"raw": {
									"language": "json"
								}
							}
						},
						"url": "http://localhost:3000/produtos/kyFEoOdnoOhM7ii2"
					},
					"response": []
				}
			]
		},
		{
			"name": "Usuario",
			"item": [
				{
					"name": "Listar usuarios",
					"request": {
						"method": "GET",
						"header": [],
						"url": "http://localhost:3000/usuarios/"
					},
					"response": []
				},
				{
					"name": "Cadastrar usuario",
					"request": {
						"method": "POST",
						"header": [],
						"body": {
							"mode": "raw",
							"raw": "{\r\n  \"nome\": \"Talissa Silva\",\r\n  \"email\": \"talissasilva@qa.com.br\",\r\n  \"password\": \"teste\",\r\n  \"administrador\": \"true\"\r\n}",
							"options": {
								"raw": {
									"language": "json"
								}
							}
						},
						"url": "http://localhost:3000/usuarios"
					},
					"response": []
				},
				{
					"name": "Editar usuário",
					"request": {
						"method": "PUT",
						"header": [
							{
								"key": "Authorization",
								"value": "{{token}}",
								"type": "text"
							}
						],
						"body": {
							"mode": "raw",
							"raw": "\r\n{\r\n  \"nome\": \"Fulanio da Silvia\",\r\n  \"email\": \"beltranio@qa.com.br\",\r\n  \"password\": \"teste\",\r\n  \"administrador\": \"true\"\r\n}",
							"options": {
								"raw": {
									"language": "json"
								}
							}
						},
						"url": "http://localhost:3000/usuarios/0uxuPY0cbmQhpEz1"
					},
					"response": []
				},
				{
					"name": "Usuarios por id",
					"protocolProfileBehavior": {
						"disableBodyPruning": true
					},
					"request": {
						"method": "GET",
						"header": [],
						"body": {
							"mode": "raw",
							"raw": "",
							"options": {
								"raw": {
									"language": "json"
								}
							}
						},
						"url": "http://localhost:3000/usuarios/BEfpfkHTtvCu7T9H"
					},
					"response": []
				},
				{
					"name": "Deletar usuario",
					"request": {
						"method": "DELETE",
						"header": [],
						"body": {
							"mode": "raw",
							"raw": ""
						},
						"url": "http://localhost:3000/usuarios/BEfpfkHTtvCu7T9H"
					},
					"response": []
				}
			]
		},
		{
			"name": "Login",
			"item": [
				{
					"name": "Login",
					"event": [
						{
							"listen": "test",
							"script": {
								"exec": [
									"const resposta = pm.response.json();\r",
									"pm.globals.set(\"token\", resposta.authorization);"
								],
								"type": "text/javascript"
							}
						}
					],
					"request": {
						"method": "POST",
						"header": [],
						"body": {
							"mode": "raw",
							"raw": "{\r\n  \"email\": \"talissasilva@qa.com.br\",\r\n  \"password\": \"teste\"\r\n}",
							"options": {
								"raw": {
									"language": "json"
								}
							}
						},
						"url": "http://localhost:3000/login"
					},
					"response": []
				}
			]
		}
	]
}